local_test/__init__.py
local_test/get_word.py
local_test/read_user.py
local_test/turn_json.py
local_test/write_user.py
nonebot_plugin_wordsnorote/Kaoyan.json
nonebot_plugin_wordsnorote/__init__.py
nonebot_plugin_wordsnorote/get_word.py
nonebot_plugin_wordsnorote/read_user.py
nonebot_plugin_wordsnorote/write_user.py
nonebot_plugin_wordsnorote-0.0.2.dist-info/LICENSE
nonebot_plugin_wordsnorote-0.0.2.dist-info/METADATA
nonebot_plugin_wordsnorote-0.0.2.dist-info/WHEEL
nonebot_plugin_wordsnorote-0.0.2.dist-info/top_level.txt
nonebot_plugin_wordsnorote-0.0.2.dist-info/RECORD
