Metadata-Version: 2.1
Name: nonebot-plugin-wordsnorote
Version: 0.0.2
Summary: a nonebot plugin to remember words
Home-page: https://github.com/GC-ZF/nonebot_plugin_wordsnorote
Author: zhangshier
Author-email: 1310446718@qq.com
Keywords: pip,nonebot2,nonebot,English,nonebot_plugin
Platform: any
Classifier: Programming Language :: Python :: 3
Classifier: License :: OSI Approved :: MIT License
Classifier: Operating System :: OS Independent
Requires-Python: >=3.7.3,<4.0
License-File: LICENSE
Requires-Dist: nonebot-plugin-apscheduler (>=0.1.3)
Requires-Dist: nonebot2 (>=2.0.0-beta.2)
Requires-Dist: nonebot-adapter-onebot (>=2.0.0b1)
Requires-Dist: nonebot-adapter-onebot
